betterlist/__init__.py
betterlist/cachefile.py
betterlist/config.py
betterlist/core.py
betterlist/keying.py
betterlist/backends/__init__.py
betterlist/backends/disk.py
betterlist/backends/memory.py
betterlist/codecs/__init__.py
betterlist/codecs/base.py
betterlist/codecs/json_codec.py
betterlist/codecs/pickle_codec.py
betterlist-0.1.2.dist-info/METADATA
betterlist-0.1.2.dist-info/WHEEL
betterlist-0.1.2.dist-info/top_level.txt
betterlist-0.1.2.dist-info/RECORD
