Metadata-Version: 2.4
Name: betterlist
Version: 0.1.2
Summary: betterlist: list() materialization with transparent caching via betterlist[iterable]
Author: You
License: MIT
Project-URL: Homepage, https://pypi.org/project/betterlist/
Requires-Python: >=3.10
